GetFileSize/__init__.py
GetFileSize/getfilesize.py
GetFilesize-1.0.0.dist-info/LICENSE.txt
GetFilesize-1.0.0.dist-info/METADATA
GetFilesize-1.0.0.dist-info/WHEEL
GetFilesize-1.0.0.dist-info/top_level.txt
GetFilesize-1.0.0.dist-info/RECORD
